wrps/__main__.py
wrps-0.1.0.dist-info/WHEEL
wrps-0.1.0.dist-info/METADATA
wrps-0.1.0.dist-info/RECORD
