Metadata-Version: 2.1
Name: wrps
Version: 0.1.0
Summary: A simple Python script reloader
License: MIT
Author: megahomyak
Author-email: g.megahomyak@gmail.com
Requires-Python: >=3.7,<4.0
Classifier: License :: OSI Approved :: MIT License
Classifier: Programming Language :: Python :: 3
Classifier: Programming Language :: Python :: 3.10
Classifier: Programming Language :: Python :: 3.7
Classifier: Programming Language :: Python :: 3.8
Classifier: Programming Language :: Python :: 3.9
Requires-Dist: watchfiles (>=0.18.0,<0.19.0)
